[
    {
        "links": "",
        "detected_ts": "2017-09-17T19:12:17.311Z",
        "viruses": "",
        "computer_domain": "",
        "computer_service": "admin#reports#activity",
        "cves": "",
        "released_ts": "2017-09-17T19:12:17.311Z",
        "severity": "low",
        "computer_id": "C02giu4l4",
        "computer_protocol": "https",
        "connector_version": "117457815989050774174",
        "computer_ip": "",
        "computer_dns": "",
        "cvss": 0.0,
        "is_error": 0,
        "vendor": "Google G Suite",
        "description": "arceotesting",
        "computer_port": 443,
        "computer_name": "",
        "name": "ted@arceogsuite.work",
        "connector_type": "token",
        "connector_name": "token",
        "connector_id": "8867055251194318375"
    },
    {
        "links": "",
        "detected_ts": "2017-09-01T07:23:05.683Z",
        "viruses": "",
        "computer_domain": "",
        "computer_service": "admin#reports#activity",
        "cves": "",
        "released_ts": "2017-09-01T07:23:05.683Z",
        "severity": "low",
        "computer_id": "C02giu4l4",
        "computer_protocol": "https",
        "connector_version": "117457815989050774174",
        "computer_ip": "",
        "computer_dns": "",
        "cvss": 0.0,
        "is_error": 0,
        "vendor": "Google G Suite",
        "description": "6385882212-g1v0lt2h7e2lpkdou37450ke5tekf9lg.apps.googleusercontent.com",
        "computer_port": 443,
        "computer_name": "",
        "name": "ted@arceogsuite.work",
        "connector_type": "token",
        "connector_name": "token",
        "connector_id": "-2328915306559283344"
    },
    {
        "links": "",
        "detected_ts": "2017-09-01T06:48:43.318Z",
        "viruses": "",
        "computer_domain": "",
        "computer_service": "admin#reports#activity",
        "cves": "",
        "released_ts": "2017-09-01T06:48:43.318Z",
        "severity": "low",
        "computer_id": "C02giu4l4",
        "computer_protocol": "https",
        "connector_version": "117457815989050774174",
        "computer_ip": "",
        "computer_dns": "",
        "cvss": 0.0,
        "is_error": 0,
        "vendor": "Google G Suite",
        "description": "6385882212-g1v0lt2h7e2lpkdou37450ke5tekf9lg.apps.googleusercontent.com",
        "computer_port": 443,
        "computer_name": "",
        "name": "ted@arceogsuite.work",
        "connector_type": "token",
        "connector_name": "token",
        "connector_id": "6855725866470625694"
    },
    {
        "links": "",
        "detected_ts": "2017-09-01T02:59:02.963Z",
        "viruses": "",
        "computer_domain": "",
        "computer_service": "admin#reports#activity",
        "cves": "",
        "released_ts": "2017-09-01T02:59:02.963Z",
        "severity": "low",
        "computer_id": "C02giu4l4",
        "computer_protocol": "https",
        "connector_version": "117457815989050774174",
        "computer_ip": "",
        "computer_dns": "",
        "cvss": 0.0,
        "is_error": 0,
        "vendor": "Google G Suite",
        "description": "google oauth 2.0 playground",
        "computer_port": 443,
        "computer_name": "",
        "name": "ted@arceogsuite.work",
        "connector_type": "token",
        "connector_name": "token",
        "connector_id": "-8711583530014895231"
    },
    {
        "links": "",
        "detected_ts": "2017-09-01T02:59:02.963Z",
        "viruses": "",
        "computer_domain": "",
        "computer_service": "admin#reports#activity",
        "cves": "",
        "released_ts": "2017-09-01T02:59:02.963Z",
        "severity": "low",
        "computer_id": "C02giu4l4",
        "computer_protocol": "https",
        "connector_version": "117457815989050774174",
        "computer_ip": "",
        "computer_dns": "",
        "cvss": 0.0,
        "is_error": 0,
        "vendor": "Google G Suite",
        "description": "google oauth 2.0 playground",
        "computer_port": 443,
        "computer_name": "",
        "name": "ted@arceogsuite.work",
        "connector_type": "token",
        "connector_name": "token",
        "connector_id": "-5147845600524065193"
    },
    {
        "links": "",
        "detected_ts": "2017-09-01T02:59:02.962Z",
        "viruses": "",
        "computer_domain": "",
        "computer_service": "admin#reports#activity",
        "cves": "",
        "released_ts": "2017-09-01T02:59:02.962Z",
        "severity": "low",
        "computer_id": "C02giu4l4",
        "computer_protocol": "https",
        "connector_version": "117457815989050774174",
        "computer_ip": "",
        "computer_dns": "",
        "cvss": 0.0,
        "is_error": 0,
        "vendor": "Google G Suite",
        "description": "google oauth 2.0 playground",
        "computer_port": 443,
        "computer_name": "",
        "name": "ted@arceogsuite.work",
        "connector_type": "token",
        "connector_name": "token",
        "connector_id": "2337658496152914681"
    },
    {
        "links": "",
        "detected_ts": "2017-09-01T02:59:02.962Z",
        "viruses": "",
        "computer_domain": "",
        "computer_service": "admin#reports#activity",
        "cves": "",
        "released_ts": "2017-09-01T02:59:02.962Z",
        "severity": "low",
        "computer_id": "C02giu4l4",
        "computer_protocol": "https",
        "connector_version": "117457815989050774174",
        "computer_ip": "",
        "computer_dns": "",
        "cvss": 0.0,
        "is_error": 0,
        "vendor": "Google G Suite",
        "description": "google oauth 2.0 playground",
        "computer_port": 443,
        "computer_name": "",
        "name": "ted@arceogsuite.work",
        "connector_type": "token",
        "connector_name": "token",
        "connector_id": "2306882022210513906"
    },
    {
        "links": "",
        "detected_ts": "2017-09-01T02:59:02.962Z",
        "viruses": "",
        "computer_domain": "",
        "computer_service": "admin#reports#activity",
        "cves": "",
        "released_ts": "2017-09-01T02:59:02.962Z",
        "severity": "low",
        "computer_id": "C02giu4l4",
        "computer_protocol": "https",
        "connector_version": "117457815989050774174",
        "computer_ip": "",
        "computer_dns": "",
        "cvss": 0.0,
        "is_error": 0,
        "vendor": "Google G Suite",
        "description": "google oauth 2.0 playground",
        "computer_port": 443,
        "computer_name": "",
        "name": "ted@arceogsuite.work",
        "connector_type": "token",
        "connector_name": "token",
        "connector_id": "-6062014434547057736"
    },
    {
        "links": "",
        "detected_ts": "2017-08-31T21:59:48.945Z",
        "viruses": "",
        "computer_domain": "",
        "computer_service": "admin#reports#activity",
        "cves": "",
        "released_ts": "2017-08-31T21:59:48.945Z",
        "severity": "low",
        "computer_id": "C02giu4l4",
        "computer_protocol": "https",
        "connector_version": "117457815989050774174",
        "computer_ip": "",
        "computer_dns": "",
        "cvss": 0.0,
        "is_error": 0,
        "vendor": "Google G Suite",
        "description": "arceotesting",
        "computer_port": 443,
        "computer_name": "",
        "name": "ted@arceogsuite.work",
        "connector_type": "token",
        "connector_name": "token",
        "connector_id": "-5016461003543349161"
    },
    {
        "links": "",
        "detected_ts": "2017-08-31T21:57:49.634Z",
        "viruses": "",
        "computer_domain": "",
        "computer_service": "admin#reports#activity",
        "cves": "",
        "released_ts": "2017-08-31T21:57:49.634Z",
        "severity": "low",
        "computer_id": "C02giu4l4",
        "computer_protocol": "https",
        "connector_version": "117457815989050774174",
        "computer_ip": "",
        "computer_dns": "",
        "cvss": 0.0,
        "is_error": 0,
        "vendor": "Google G Suite",
        "description": "arceotesting",
        "computer_port": 443,
        "computer_name": "",
        "name": "ted@arceogsuite.work",
        "connector_type": "token",
        "connector_name": "token",
        "connector_id": "2533966273569372021"
    },
    {
        "links": "",
        "detected_ts": "2017-08-31T21:49:12.443Z",
        "viruses": "",
        "computer_domain": "",
        "computer_service": "admin#reports#activity",
        "cves": "",
        "released_ts": "2017-08-31T21:49:12.443Z",
        "severity": "low",
        "computer_id": "C02giu4l4",
        "computer_protocol": "https",
        "connector_version": "117457815989050774174",
        "computer_ip": "",
        "computer_dns": "",
        "cvss": 0.0,
        "is_error": 0,
        "vendor": "Google G Suite",
        "description": "arceotesting",
        "computer_port": 443,
        "computer_name": "",
        "name": "ted@arceogsuite.work",
        "connector_type": "token",
        "connector_name": "token",
        "connector_id": "8914944572125415711"
    },
    {
        "links": "",
        "detected_ts": "2017-08-31T20:59:02.730Z",
        "viruses": "",
        "computer_domain": "",
        "computer_service": "admin#reports#activity",
        "cves": "",
        "released_ts": "2017-08-31T20:59:02.730Z",
        "severity": "low",
        "computer_id": "C02giu4l4",
        "computer_protocol": "https",
        "connector_version": "117457815989050774174",
        "computer_ip": "",
        "computer_dns": "",
        "cvss": 0.0,
        "is_error": 0,
        "vendor": "Google G Suite",
        "description": "google oauth 2.0 playground",
        "computer_port": 443,
        "computer_name": "",
        "name": "ted@arceogsuite.work",
        "connector_type": "token",
        "connector_name": "token",
        "connector_id": "5502657658625754623"
    },
    {
        "links": "",
        "detected_ts": "2017-08-30T21:37:20.509Z",
        "viruses": "",
        "computer_domain": "",
        "computer_service": "admin#reports#activity",
        "cves": "",
        "released_ts": "2017-08-30T21:37:20.509Z",
        "severity": "low",
        "computer_id": "C02giu4l4",
        "computer_protocol": "https",
        "connector_version": "117457815989050774174",
        "computer_ip": "",
        "computer_dns": "",
        "cvss": 0.0,
        "is_error": 0,
        "vendor": "Google G Suite",
        "description": "zoom",
        "computer_port": 443,
        "computer_name": "",
        "name": "ted@arceogsuite.work",
        "connector_type": "token",
        "connector_name": "token",
        "connector_id": "8325980960601581913"
    },
    {
        "links": "",
        "detected_ts": "2017-06-21T21:40:57.086Z",
        "viruses": "",
        "computer_domain": "",
        "computer_service": "admin#reports#activity",
        "cves": "",
        "released_ts": "2017-06-21T21:40:57.086Z",
        "severity": "low",
        "computer_id": "C02giu4l4",
        "computer_protocol": "https",
        "connector_version": "117457815989050774174",
        "computer_ip": "",
        "computer_dns": "",
        "cvss": 0.0,
        "is_error": 0,
        "vendor": "Google G Suite",
        "description": "slack",
        "computer_port": 443,
        "computer_name": "",
        "name": "ted@arceogsuite.work",
        "connector_type": "token",
        "connector_name": "token",
        "connector_id": "-8817430028663674831"
    },
    {
        "links": "",
        "detected_ts": "2017-05-30T12:12:14.138Z",
        "viruses": "",
        "computer_domain": "",
        "computer_service": "admin#reports#activity",
        "cves": "",
        "released_ts": "2017-05-30T12:12:14.138Z",
        "severity": "low",
        "computer_id": "C02giu4l4",
        "computer_protocol": "https",
        "connector_version": "117457815989050774174",
        "computer_ip": "",
        "computer_dns": "",
        "cvss": 0.0,
        "is_error": 0,
        "vendor": "Google G Suite",
        "description": "google apis explorer",
        "computer_port": 443,
        "computer_name": "",
        "name": "ted@arceogsuite.work",
        "connector_type": "token",
        "connector_name": "token",
        "connector_id": "474812564604329935"
    },
    {
        "links": "",
        "detected_ts": "2017-05-19T09:03:53.350Z",
        "viruses": "",
        "computer_domain": "",
        "computer_service": "admin#reports#activity",
        "cves": "",
        "released_ts": "2017-05-19T09:03:53.350Z",
        "severity": "low",
        "computer_id": "C02giu4l4",
        "computer_protocol": "https",
        "connector_version": "117457815989050774174",
        "computer_ip": "",
        "computer_dns": "",
        "cvss": 0.0,
        "is_error": 0,
        "vendor": "Google G Suite",
        "description": "bigquery client tools",
        "computer_port": 443,
        "computer_name": "",
        "name": "ted@arceogsuite.work",
        "connector_type": "token",
        "connector_name": "token",
        "connector_id": "8251388755854757384"
    },
    {
        "links": "",
        "detected_ts": "2017-05-19T09:03:26.382Z",
        "viruses": "",
        "computer_domain": "",
        "computer_service": "admin#reports#activity",
        "cves": "",
        "released_ts": "2017-05-19T09:03:26.382Z",
        "severity": "low",
        "computer_id": "C02giu4l4",
        "computer_protocol": "https",
        "connector_version": "117457815989050774174",
        "computer_ip": "",
        "computer_dns": "",
        "cvss": 0.0,
        "is_error": 0,
        "vendor": "Google G Suite",
        "description": "bigquery client tools",
        "computer_port": 443,
        "computer_name": "",
        "name": "ted@arceogsuite.work",
        "connector_type": "token",
        "connector_name": "token",
        "connector_id": "-2535879709423784298"
    },
    {
        "links": "",
        "detected_ts": "2017-05-03T22:19:10.616Z",
        "viruses": "",
        "computer_domain": "",
        "computer_service": "admin#reports#activity",
        "cves": "",
        "released_ts": "2017-05-03T22:19:10.616Z",
        "severity": "low",
        "computer_id": "C02giu4l4",
        "computer_protocol": "https",
        "connector_version": "117457815989050774174",
        "computer_ip": "",
        "computer_dns": "",
        "cvss": 0.0,
        "is_error": 0,
        "vendor": "Google G Suite",
        "description": "google apis explorer",
        "computer_port": 443,
        "computer_name": "",
        "name": "ted@arceogsuite.work",
        "connector_type": "token",
        "connector_name": "token",
        "connector_id": "6867758963898138915"
    },
    {
        "links": "",
        "detected_ts": "2017-05-03T21:48:45.257Z",
        "viruses": "",
        "computer_domain": "",
        "computer_service": "admin#reports#activity",
        "cves": "",
        "released_ts": "2017-05-03T21:48:45.257Z",
        "severity": "low",
        "computer_id": "C02giu4l4",
        "computer_protocol": "https",
        "connector_version": "117457815989050774174",
        "computer_ip": "",
        "computer_dns": "",
        "cvss": 0.0,
        "is_error": 0,
        "vendor": "Google G Suite",
        "description": "google apis explorer",
        "computer_port": 443,
        "computer_name": "",
        "name": "ted@arceogsuite.work",
        "connector_type": "token",
        "connector_name": "token",
        "connector_id": "-6805991745624448825"
    },
    {
        "links": "",
        "detected_ts": "2017-04-22T01:14:44.980Z",
        "viruses": "",
        "computer_domain": "",
        "computer_service": "admin#reports#activity",
        "cves": "",
        "released_ts": "2017-04-22T01:14:44.980Z",
        "severity": "low",
        "computer_id": "C02giu4l4",
        "computer_protocol": "https",
        "connector_version": "113275966229865943187",
        "computer_ip": "",
        "computer_dns": "",
        "cvss": 0.0,
        "is_error": 0,
        "vendor": "Google G Suite",
        "description": "mindmup 2.0 for google drive",
        "computer_port": 443,
        "computer_name": "",
        "name": "jim@arceogsuite.work",
        "connector_type": "token",
        "connector_name": "token",
        "connector_id": "-3561053003629786116"
    },
    {
        "links": "",
        "detected_ts": "2017-04-19T16:06:00.282Z",
        "viruses": "",
        "computer_domain": "",
        "computer_service": "admin#reports#activity",
        "cves": "",
        "released_ts": "2017-04-19T16:06:00.282Z",
        "severity": "low",
        "computer_id": "C02giu4l4",
        "computer_protocol": "https",
        "connector_version": "117457815989050774174",
        "computer_ip": "",
        "computer_dns": "",
        "cvss": 0.0,
        "is_error": 0,
        "vendor": "Google G Suite",
        "description": "google apis explorer",
        "computer_port": 443,
        "computer_name": "",
        "name": "ted@arceogsuite.work",
        "connector_type": "token",
        "connector_name": "token",
        "connector_id": "-9189798195808608511"
    },
    {
        "links": "",
        "detected_ts": "2017-04-19T14:22:36.647Z",
        "viruses": "",
        "computer_domain": "",
        "computer_service": "admin#reports#activity",
        "cves": "",
        "released_ts": "2017-04-19T14:22:36.647Z",
        "severity": "low",
        "computer_id": "C02giu4l4",
        "computer_protocol": "https",
        "connector_version": "117457815989050774174",
        "computer_ip": "",
        "computer_dns": "",
        "cvss": 0.0,
        "is_error": 0,
        "vendor": "Google G Suite",
        "description": "arceotesting",
        "computer_port": 443,
        "computer_name": "",
        "name": "ted@arceogsuite.work",
        "connector_type": "token",
        "connector_name": "token",
        "connector_id": "-2932366347214445830"
    },
    {
        "links": "",
        "detected_ts": "2017-04-18T00:35:43.190Z",
        "viruses": "",
        "computer_domain": "",
        "computer_service": "admin#reports#activity",
        "cves": "",
        "released_ts": "2017-04-18T00:35:43.190Z",
        "severity": "low",
        "computer_id": "C02giu4l4",
        "computer_protocol": "https",
        "connector_version": "117457815989050774174",
        "computer_ip": "",
        "computer_dns": "",
        "cvss": 0.0,
        "is_error": 0,
        "vendor": "Google G Suite",
        "description": "google oauth 2.0 playground",
        "computer_port": 443,
        "computer_name": "",
        "name": "ted@arceogsuite.work",
        "connector_type": "token",
        "connector_name": "token",
        "connector_id": "7285505999114550906"
    },
    {
        "links": "",
        "detected_ts": "2017-04-18T00:35:43.160Z",
        "viruses": "",
        "computer_domain": "",
        "computer_service": "admin#reports#activity",
        "cves": "",
        "released_ts": "2017-04-18T00:35:43.160Z",
        "severity": "low",
        "computer_id": "C02giu4l4",
        "computer_protocol": "https",
        "connector_version": "117457815989050774174",
        "computer_ip": "",
        "computer_dns": "",
        "cvss": 0.0,
        "is_error": 0,
        "vendor": "Google G Suite",
        "description": "google oauth 2.0 playground",
        "computer_port": 443,
        "computer_name": "",
        "name": "ted@arceogsuite.work",
        "connector_type": "token",
        "connector_name": "token",
        "connector_id": "4840606511208832912"
    },
    {
        "links": "",
        "detected_ts": "2017-04-17T18:35:43.049Z",
        "viruses": "",
        "computer_domain": "",
        "computer_service": "admin#reports#activity",
        "cves": "",
        "released_ts": "2017-04-17T18:35:43.049Z",
        "severity": "low",
        "computer_id": "C02giu4l4",
        "computer_protocol": "https",
        "connector_version": "117457815989050774174",
        "computer_ip": "",
        "computer_dns": "",
        "cvss": 0.0,
        "is_error": 0,
        "vendor": "Google G Suite",
        "description": "google oauth 2.0 playground",
        "computer_port": 443,
        "computer_name": "",
        "name": "ted@arceogsuite.work",
        "connector_type": "token",
        "connector_name": "token",
        "connector_id": "5065930671971366959"
    },
    {
        "links": "",
        "detected_ts": "2017-04-12T23:40:15.326Z",
        "viruses": "",
        "computer_domain": "",
        "computer_service": "admin#reports#activity",
        "cves": "",
        "released_ts": "2017-04-12T23:40:15.326Z",
        "severity": "low",
        "computer_id": "C02giu4l4",
        "computer_protocol": "https",
        "connector_version": "117457815989050774174",
        "computer_ip": "",
        "computer_dns": "",
        "cvss": 0.0,
        "is_error": 0,
        "vendor": "Google G Suite",
        "description": "6385882212-ccc3plq44dp2v7ch1uar4crbqbj14mno.apps.googleusercontent.com",
        "computer_port": 443,
        "computer_name": "",
        "name": "ted@arceogsuite.work",
        "connector_type": "token",
        "connector_name": "token",
        "connector_id": "-615652799259920396"
    },
    {
        "links": "",
        "detected_ts": "2017-04-12T20:55:30.966Z",
        "viruses": "",
        "computer_domain": "",
        "computer_service": "admin#reports#activity",
        "cves": "",
        "released_ts": "2017-04-12T20:55:30.966Z",
        "severity": "low",
        "computer_id": "C02giu4l4",
        "computer_protocol": "https",
        "connector_version": "117457815989050774174",
        "computer_ip": "",
        "computer_dns": "",
        "cvss": 0.0,
        "is_error": 0,
        "vendor": "Google G Suite",
        "description": "google apis explorer",
        "computer_port": 443,
        "computer_name": "",
        "name": "ted@arceogsuite.work",
        "connector_type": "token",
        "connector_name": "token",
        "connector_id": "-8251978305394272870"
    }
]